ask_test_util/__init__.py
ask_test_util/ask_test_util.py
ask_test_util-0.1.0.dist-info/LICENSE
ask_test_util-0.1.0.dist-info/METADATA
ask_test_util-0.1.0.dist-info/WHEEL
ask_test_util-0.1.0.dist-info/top_level.txt
ask_test_util-0.1.0.dist-info/RECORD
