Metadata-Version: 2.1
Name: ask-test-util
Version: 0.1.0
Summary: Test your Alexa skills locally
Home-page: https://github.com/shuds13/pyexample
Author: João Marcos
Author-email: shudson@anl.gov
License: BSD 2-clause
Platform: UNKNOWN
Classifier: Development Status :: 1 - Planning
Classifier: Intended Audience :: Science/Research
Classifier: License :: OSI Approved :: BSD License
Classifier: Operating System :: POSIX :: Linux
Classifier: Programming Language :: Python :: 2
Classifier: Programming Language :: Python :: 2.7
Classifier: Programming Language :: Python :: 3
Classifier: Programming Language :: Python :: 3.4
Classifier: Programming Language :: Python :: 3.5
Requires-Dist: ask-sdk-core
Requires-Dist: ask-smapi-model
Requires-Dist: ask-smapi-sdk
